gvizlib/__init__.py
gvizlib/base.py
gvizlib/cache.py
gvizlib/chart.py
gvizlib/dashboard.py
gvizlib/table.py
gvizlib-0.0.1.dist-info/METADATA
gvizlib-0.0.1.dist-info/WHEEL
gvizlib-0.0.1.dist-info/top_level.txt
gvizlib-0.0.1.dist-info/zip-safe
gvizlib-0.0.1.dist-info/RECORD
