Metadata-Version: 2.1
Name: gvizlib
Version: 0.0.1
Summary: A package for the Google Visualization API
Home-page: https://www.lockhartlab.org
Author: C. Lockhart
Author-email: chris@lockhartlab.org
License: UNKNOWN
Platform: UNKNOWN
Requires-Dist: numpy
Requires-Dist: pandas
